musc-0.1.2.dist-info/METADATA
musc-0.1.2.dist-info/WHEEL
musc-0.1.2.dist-info/entry_points.txt
musc/__init__.py
musc/adaptors/drift_detectors/a.py
musc/adaptors/drift_detectors/river/a.py
musc/adaptors/drift_detectors/river/with_kdp/__init__.py
musc/adaptors/models.py
musc/commons.py
musc/eval/a.py
musc/eval/a2.py
musc/eval/active_count.py
musc/eval/high_level.py
musc/high_level/__init__.py
musc/high_level/drift_detectors/__init__.py
musc/high_level/drift_detectors/river/__init__.py
musc/hpo/a.py
musc/hpo/distr/a.py
musc/hpo/distr/high_level.py
musc/hpo/high_level/a.py
musc/hpo/high_level/helper.py
musc/hpo/res_pool/base.py
musc/hpo/res_pool/global_.py
musc/hpo/res_pool/torch_device.py
musc/service/a.py
musc/service/concepts/a.py
musc/service/concepts/high_level/a.py
musc/service/concepts/high_level/no_clone.py
musc/service/errors.py
musc/service/high_level.py
musc/service/impl/data_history/base.py
musc/service/impl/data_history/in_memory.py
musc/service/impl/dd_process/a.py
musc/service/impl/dd_process/dh_walker.py
musc/service/impl/dd_process/stats.py
musc/service/impl/model_wrapper.py
musc-0.1.2.dist-info/RECORD
