Metadata-Version: 2.1
Name: musc
Version: 0.1.2
Summary: A library to construct concept drift adaptive model services.
Author-Email: YANG Qi <y3tothe6@outlook.com>
License: MIT
Requires-Python: >=3.11
Requires-Dist: flask>=3.0.0
Requires-Dist: gevent>=23.9.1
Requires-Dist: joblib>=1.3.2
Requires-Dist: numpy>=1.26.3
Requires-Dist: readerwriterlock>=1.0.9
Requires-Dist: river>=0.19.0
Requires-Dist: pandas>=2.1.4
Requires-Dist: sortedcontainers>=2.4.0
Requires-Dist: cloudpickle>=3.0.0
